pharia_skill/__init__.py
pharia_skill/cli.py
pharia_skill/componentize-py.toml
pharia_skill/pharia_skill_cli.py
pharia_skill/py.typed
pharia_skill/skill.py
pharia_skill/studio.py
pharia_skill/bindings/__init__.py
pharia_skill/bindings/types.py
pharia_skill/bindings/exports/__init__.py
pharia_skill/bindings/exports/message_stream.py
pharia_skill/bindings/exports/skill_handler.py
pharia_skill/bindings/imports/__init__.py
pharia_skill/bindings/imports/chunking.py
pharia_skill/bindings/imports/document_index.py
pharia_skill/bindings/imports/inference.py
pharia_skill/bindings/imports/language.py
pharia_skill/bindings/imports/streaming_output.py
pharia_skill/bindings/imports/tool.py
pharia_skill/csi/__init__.py
pharia_skill/csi/chunking.py
pharia_skill/csi/csi.py
pharia_skill/csi/document_index.py
pharia_skill/csi/language.py
pharia_skill/csi/inference/__init__.py
pharia_skill/csi/inference/inference.py
pharia_skill/csi/inference/tool.py
pharia_skill/csi/inference/types.py
pharia_skill/llama3/__init__.py
pharia_skill/llama3/message.py
pharia_skill/llama3/request.py
pharia_skill/llama3/response.py
pharia_skill/llama3/tool.py
pharia_skill/llama3/tool_call.py
pharia_skill/message_stream/__init__.py
pharia_skill/message_stream/decorator.py
pharia_skill/message_stream/wit_writer.py
pharia_skill/message_stream/writer.py
pharia_skill/testing/__init__.py
pharia_skill/testing/stub.py
pharia_skill/testing/dev/__init__.py
pharia_skill/testing/dev/chunking.py
pharia_skill/testing/dev/client.py
pharia_skill/testing/dev/csi.py
pharia_skill/testing/dev/document_index.py
pharia_skill/testing/dev/inference.py
pharia_skill/testing/dev/language.py
pharia_skill/testing/dev/logfire.py
pharia_skill/testing/dev/streaming_output.py
pharia_skill/testing/dev/tool.py
pharia_skill/wit/all.wit
pharia_skill/wit/skill.wit
pharia_skill/wit_csi/__init__.py
pharia_skill/wit_csi/chunking.py
pharia_skill/wit_csi/csi.py
pharia_skill/wit_csi/document_index.py
pharia_skill/wit_csi/inference.py
pharia_skill-0.20.0.dist-info/METADATA
pharia_skill-0.20.0.dist-info/WHEEL
pharia_skill-0.20.0.dist-info/entry_points.txt
pharia_skill-0.20.0.dist-info/licenses/LICENSE
pharia_skill-0.20.0.dist-info/licenses/NOTICE
pharia_skill-0.20.0.dist-info/RECORD
