Metadata-Version: 2.4
Name: pharia-skill
Version: 0.20.0
Summary: SDK for building Python skills for Pharia Kernel
Project-URL: Homepage, https://github.com/Aleph-Alpha/pharia-kernel-sdk-py
Project-URL: Documentation, https://pharia-skill.readthedocs.io
Project-URL: Repository, https://github.com/Aleph-Alpha/pharia-kernel-sdk-py
Project-URL: Changelog, https://github.com/Aleph-Alpha/pharia-kernel-sdk-py/blob/main/CHANGELOG.md
Author-email: Markus Klein <markus.klein@aleph-alpha.com>, Benjamin Brandt <benjamin.brandt@aleph-alpha.com>, Moritz Althaus <moritz.althaus@aleph-alpha.com>, Jia Ho Lee <jiaho.lee@aleph-alpha.com>, Lars Rass <lars.rass@aleph-alpha.com>
License-Expression: Apache-2.0
License-File: LICENSE
License-File: NOTICE
Requires-Python: ~=3.11.0
Requires-Dist: componentize-py<0.18,>=0.17.0
Requires-Dist: opentelemetry-exporter-otlp-proto-http<2,>=1.28.1
Requires-Dist: opentelemetry-sdk<2,>=1.28.1
Requires-Dist: pharia-skill-cli>=0.4.9
Requires-Dist: pydantic-core==2.33.2
Requires-Dist: pydantic==2.11.7
Requires-Dist: python-dotenv<2,>=1.0.1
Requires-Dist: requests<3,>=2.32.3
Requires-Dist: rich<15,>=13.7.0
Requires-Dist: typer<0.16,>=0.15.4
